topbotsapi/__init__.py
topbotsapi/api.py
topbotsapi/classes.py
topbotsapi/exceptions.py
topbotsapi-1.1.2.dist-info/LICENSE
topbotsapi-1.1.2.dist-info/METADATA
topbotsapi-1.1.2.dist-info/WHEEL
topbotsapi-1.1.2.dist-info/top_level.txt
topbotsapi-1.1.2.dist-info/RECORD
