Metadata-Version: 2.1
Name: topbotsapi
Version: 1.1.2
Summary: Top Discord Bots Resmi api
Home-page: https://topdiscordbots.tk
Author: Mister Jevil
Author-email: dogasezer2002@gmail.com
License: UNKNOWN
Platform: UNKNOWN
Requires-Python: >=3.6
